{
  "project_info": {
    "project_number": "568108543532",
    "project_id": "movecity-unit",
    "storage_bucket": "movecity-unit.firebasestorage.app"
  },
  "client": [
    {
      "client_info": {
        "mobilesdk_app_id": "1:568108543532:android:a30f3cc130f9347e55ab89",
        "android_client_info": {
          "package_name": "com.example.movecity"
        }
      },
      "oauth_client": [],
      "api_key": [
        {
          "current_key": "AIzaSyD3lCnTJxdK4lvV2MGTdcmB8_NbE8kYGoo"
        }
      ],
      "services": {
        "appinvite_service": {
          "other_platform_oauth_client": []
        }
      }
    }
  ],
  "configuration_version": "1"
}